Workbook

Sheet 🏠 Dashboard
A1: BLUSHES & BRUSHES
A2: Summer 2026 Lead Generation Campaign — Command Centre
A5: Total Leads | B5: Trials Booked | C5: Enrolled | D5: Total Spend ₹ | E5: Avg CPL ₹ | F5: Revenue ₹
A6: ='💰 Budget Tracker'!F20 | B6: ='💰 Budget Tracker'!H20 | C6: ='💰 Budget Tracker'!I20 | D6: ='💰 Budget Tracker'!E20 | E6: ='💰 Budget Tracker'!G20 | F6: ='💰 Budget Tracker'!I20*20000
A8: QUICK NAVIGATION
A9: → ✅ Setup Checklist | B9: Track all technical setup tasks
A10: → 🎬 Content Tracker | B10: Track every video from filmed to posted
A11: → 📅 Weekly Ops | B11: Day-by-day task calendar for 8 weeks
A12: → 📲 Lead Follow-Up SOP | B12: Step-by-step WhatsApp follow-up guide
A13: → 💰 Budget Tracker | B13: Track ad spend, leads, and cost-per-lead
A15: SUMMER CAMPAIGN GOAL
A16: Budget | B16: ₹5,000 – ₹10,000/month (₹165 – ₹330/day)
A17: Target Leads | B17: 50–150 leads per month
A18: Target CPL | B18: Below ₹150 per lead
A19: Trial Conversion | B19: 40–60% of leads → trial class
A20: Enrolment Rate | B20: 30–50% of trial attendees → enrolled
A21: Campaign Period | B21: May – August 2026 (Summer)
A22: Landing Page | B22: Paste Vercel URL here after deployment →

Sheet ✅ Setup Checklist
A1: BLUSHES & BRUSHES — MASTER SETUP CHECKLIST
A2: Summer 2026 Lead Campaign | Mark tasks Done as you complete them
A4: # | B4: Category | C4: Task | D4: Who | E4: Effort | F4: Status | G4: Notes / Link
A5: 1 | B5: Landing Page | C5: Confirm landing page runs on localhost:3000 | D5: Dev | E5: 5 min | F5: ✅ Done | G5: Run: npm run dev
A6: 2 | B6: Landing Page | C6: Deploy to Vercel (free tier, no domain needed) | D6: Dev | E6: 10 min | F6: 🔄 In Progress | G6: vercel --yes --prod
A7: 3 | B7: Landing Page | C7: Add live Vercel URL to this sheet in Notes column (row 2) | D7: Both | E7: 2 min | F7: ⬜ To Do | G7: Paste URL when deployment done
A8: 4 | B8: Landing Page | C8: Test form submission end-to-end on live URL | D8: Both | E8: 5 min | F8: ⬜ To Do | G8: Fill form → check Google Sheet
A9: 5 | B9: Landing Page | C9: Share live URL with Urvashi for review | D9: Dev | E9: 2 min | F9: ⬜ To Do | G9: WhatsApp or email
A10: 6 | B10: Meta Pixel | C10: Go to Meta Events Manager → Create Data Source → Web Pixel | D10: Urvashi | E10: 10 min | F10: ⬜ To Do | G10: business.facebook.com → Events Manager
A11: 7 | B11: Meta Pixel | C11: Copy Pixel ID and paste into .env.local (NEXT_PUBLIC_META_PIXEL_ID) | D11: Dev | E11: 5 min | F11: ⬜ To Do | G11: Redeploy on Vercel after change
A12: 8 | B12: Meta Pixel | C12: Add Pixel ID to Vercel Dashboard → Settings → Env Variables | D12: Dev | E12: 5 min | F12: ⬜ To Do | G12: Also add WEBHOOK_URL there
A13: 9 | B13: Meta Pixel | C13: Verify Pixel fires on landing page using Meta Pixel Helper extension | D13: Dev | E13: 10 min | F13: ⬜ To Do | G13: Chrome extension: Meta Pixel Helper
A14: 10 | B14: Automation | C14: Create free Make.com account at make.com | D14: Dev | E14: 5 min | F14: ⬜ To Do | G14: make.com/register
A15: 11 | B15: Automation | C15: Create new scenario: Webhook → Google Sheets → WhatsApp | D15: Dev | E15: 30 min | F15: ⬜ To Do | G15: See playbook Part 3 for step-by-step
... A31: 27 | B31: Instagram | C31: Post first Reel (studio tour or course graphic) | D31: Urvashi | E31: 20 min | F31: ⬜ To Do | G31: Caption template in ad brief doc

Sheet 🎬 Content Tracker
A1: CONTENT CREATION TRACKER
A2: Track every video and post from script → filmed → edited → posted
A4: # | B4: Format | C4: Angle / Topic | D4: Script Ready? | E4: Filmed? | F4: Edited? | G4: Posted? | H4: Post Date | I4: Platform | J4: Notes
A5: 1 | B5: 15s Reel | C5: Angle A — Don't Waste Your Summer (Hindi) | D5: ✅ Done | E5: ⬜ To Do | F5: ⬜ To Do | G5: ⬜ To Do | I5: Instagram Reels | J5: Script in Brief doc p.3
A6: 2 | B6: 30s Feed Ad | C6: Angle B — Passion into Paycheque (Hindi) | D6: ✅ Done | E6: ⬜ To Do | F6: ⬜ To Do | G6: ⬜ To Do | I6: Facebook + IG Feed | J6: Script in Brief doc p.4
A7: 3 | B7: 15s Reel | C7: Angle C — Career Switch (Hindi) | D7: ✅ Done | E7: ⬜ To Do | F7: ⬜ To Do | G7: ⬜ To Do | I7: Instagram Reels | J7: Script in Brief doc p.5
A8: 4 | B8: 10s Story | C8: Angle D — Only 2 Seats Left (film WEEKLY) | D8: ✅ Done | E8: ⬜ To Do | F8: ⬜ To Do | G8: ⬜ To Do | I8: Stories + Reels | J8: Re-film every Monday
A9: 5 | B9: 45s Video | C9: Angle E — Founder Story (Urvashi to camera) | D9: ✅ Done | E9: ⬜ To Do | F9: ⬜ To Do | G9: ⬜ To Do | I9: IG + FB Feed | J9: Most important — retargeting
A10: 6 | B10: Reel | C10: Studio tour — wide shot salon pan | D10: ⬜ To Do | E10: ⬜ To Do | F10: ⬜ To Do | G10: ⬜ To Do | I10: Instagram Reels | J10: Shot #2 from shot list
A11: 7 | B11: Reel | C11: Bridal makeup before/after reveal | D11: ⬜ To Do | E11: ⬜ To Do | F11: ⬜ To Do | G11: ⬜ To Do | I11: Instagram Reels | J11: Transformation = high shares
A12: 8 | B12: Carousel | C12: All 3 courses — course graphic carousel | D12: ✅ Done | E12: ⬜ To Do | F12: ⬜ To Do | G12: ⬜ To Do | I12: Instagram Feed | J12: Use existing course PNGs
A13: 9 | B13: Reel | C13: Nail art timelapse (any design) | D13: ⬜ To Do | E13: ⬜ To Do | F13: ⬜ To Do | G13: ⬜ To Do | I13: Instagram Reels | J13: Top-down, tripod if possible
A14: 10 | B14: Story | C14: Student testimonial (screen-record DM or video) | D14: ⬜ To Do | E14: ⬜ To Do | F14: ⬜ To Do | G14: ⬜ To Do | I14: Stories + Highlights | J14: Ask recent graduate
A15: 11 | B15: Reel | C15: Urvashi teaching student 1-on-1 | D15: ⬜ To Do | E15: ⬜ To Do | F15: ⬜ To Do | G15: ⬜ To Do | I15: Instagram Reels | J15: Side angle, natural convo
A16: 12 | B16: Post | C16: Certificate ceremony — graduation moment | D16: ⬜ To Do | E16: ⬜ To Do | F16: ⬜ To Do | G16: ⬜ To Do | I16: Instagram Feed | J16: Warm, celebratory caption
... A19: 15 | B19: Reel | C19: Wk 7 — Last 2 Seats urgency (film fresh) | D19: ⬜ To Do | E19: ⬜ To Do | F19: ⬜ To Do | G19: ⬜ To Do | I19: Reels + Stories | J19: Film in week 7 specifically

Sheet 📅 Weekly Ops
A1: 8-WEEK SUMMER OPERATIONS CALENDAR
A2: Daily task breakdown by week | Check off each week when complete
A4: Week | B4: Dates | C4: Mon | D4: Tue (Post) | E4: Wed | F4: Thu (Post) | G4: Fri | H4: Sat (Post) | I4: Sun | J4: Ad Check | K4: Done?
A5: 1 | B5: Launch Week | C5: Film all shot list | D5: Post: Studio Tour Reel | E5: Edit videos | F5: Post: Course Carousel | G5: Upload ads to Meta | H5: Post: Meet Urvashi video | I5: Review ad performance | J5: Launch Ad Set 1 + 2. Budget ₹200/day | K5: ⬜ To Do
A6: 2 | B6: Wk 2 | C6: Reply all DMs | D6: Post: Student testimonial | E6: Film new content | F6: Post: Day in the life | G6: Film Angle D (fresh) | H6: Post: Nail art timelapse | I6: Review leads in Sheet | J6: Boost top organic Reel ₹200/day | K6: ⬜ To Do
A7: 3 | B7: Wk 3 | C7: Reply all DMs | D7: Post: Before/after bridal | E7: Check ad CPL | F7: Post: 5 reasons Reel | G7: Kill weak ad set | H7: Post: FAQ Stories (polls) | I7: Count leads this week | J7: Kill ad set CPL >₹300. Double winner | K7: ⬜ To Do
A8: 4 | B8: Wk 4 | C8: Reply all DMs | D8: Post: Certificate ceremony | E8: Prep Q&A Live | F8: Post: ₹20k breakdown | G8: Promote Live | H8: Live Q&A 30 min on IG | I8: Review pipeline | J8: Launch Retargeting Ad Set (Angle E) | K8: ⬜ To Do
A9: 5 | B9: Wk 5 | C9: Reply all DMs | D9: Post: Student transform | E9: Scale winner 2x | F9: Post: Nail tutorial | G9: Film Angle D (fresh) | H9: Post: Seats filling up Reel | I9: Count total leads | J9: Scale best ad set to ₹300/day | K9: ⬜ To Do
A10: 6 | B10: Wk 6 | C10: Reply all DMs | D10: Post: New batch announce | E10: Film BTS content | F10: Post: BTS sourcing | G10: Film Angle D (fresh) | H10: Post: Founder Q&A Stories | I10: Mid-campaign review | J10: Run Angle D urgency ad separately | K10: ⬜ To Do
A11: 7 | B11: Wk 7 | C11: Reply all DMs | D11: Post: Last 2 seats Reel | E11: Prepare closing ads | F11: Post: Graduate story | G11: Max budget winner | H11: Post: Summer recap carousel | I11: Count enrolled leads | J11: Max budget on best performer | K11: ⬜ To Do
A12: 8 | B12: Wk 8 | C12: Reply all DMs | D12: Post: New batch announce | E12: Prep next campaign | F12: Post: Early-bird offer | G12: Export leads list | H12: Post: Thank-you video | I12: Full campaign debrief | J12: Lookalike audience from leads list | K12: ⬜ To Do

Sheet 📲 Lead Follow-Up SOP
A1: LEAD FOLLOW-UP SOP (STANDARD OPERATING PROCEDURE)
A2: Every lead that submits the form must go through all these steps in order
A4: Step | B4: Trigger | C4: Who | D4: Action | E4: Time Limit | F4: Script / Template | G4: Status Track
A5: 1 | B5: Form submitted | C5: Make.com | D5: Auto-send WhatsApp confirmation to lead | E5: Instant | F5: "Hi [Name]! 👋 Thanks for your interest in Blushes & Brushes! Urvashi will WhatsApp you shortly to schedule your free trial 💄 📍 Ramesh Nagar, Delhi | 76784 46364" | G5: Automated
A6: 2 | B6: Form submitted | C6: Make.com | D6: Add row to Google Sheet BB Leads | E6: Instant | F6: Columns: Timestamp, Name, Phone, Course, Source, Status=New | G6: Automated
A7: 3 | B7: Make.com notifies Urvashi | C7: Urvashi | D7: Send personal WhatsApp voice note to lead | E7: < 15 min | F7: "Hi [Name], main Urvashi hoon, Blushes & Brushes se. Aapka interest dekh ke bahut khushi hui! Kya hum aapki free trial class schedule kar sakte hain?" | G7: Manual
A8: 4 | B8: Lead responded | C8: Urvashi | D8: Send 2–3 student photos + salon images | E8: < 30 min | F8: Share: best bridal result, happy student with certificate, studio shot | G8: Manual
A9: 5 | B9: Lead showed interest | C9: Urvashi | D9: Offer 2 specific date/time slots for trial | E9: Same day | F9: "Aapke liye Tuesday 11am ya Thursday 3pm — kaunsa better hai?" (Always give 2 options, not open-ended) | G9: Manual
A10: 6 | B10: Trial date confirmed | C10: Urvashi | D10: Send confirmation + address on WhatsApp | E10: Immediately | F10: "Confirmed! [Date] [Time] at Blushes & Brushes, B 1/1 Double Storey, Ramesh Nagar, Opp. Subway. See you then! 🎉" | G10: Manual
A11: 7 | B11: 1 day before trial | C11: Urvashi | D11: Send reminder WhatsApp | E11: Day before | F11: "Hi [Name]! Just a reminder — your free trial class is tomorrow at [Time]. Looking forward to meeting you! 💄" | G11: Manual
A12: 8 | B12: No response after 2 days | C12: Urvashi | D12: Send single polite follow-up | E12: Day 2 | F12: "Hi [Name], did you get a chance to think about it? The next batch has limited seats — happy to answer any questions 😊" | G12: Manual
A13: 9 | B13: Still no response D5 | C13: Urvashi | D13: Final follow-up with social proof | E13: Day 5 | F13: "Hi [Name], sharing a quick video of one of our recent graduates [share video]. Would love to have you visit 🙏" | G13: Manual
A14: 10 | B14: Trial attended | C14: Urvashi | D14: Follow up same evening for enrolment | E14: Same evening | F14: "So lovely meeting you today! Are you ready to join the batch? I can hold your seat for 24 hours 🌸" | G14: Manual
A15: 11 | B15: Enrolled | C15: Urvashi | D15: Add to WhatsApp batch group + update Sheet | E15: Immediately | F15: Update Google Sheet: Status → Enrolled. Add to batch WhatsApp group. | G15: Manual
A16: 12 | B16: Not enrolling yet | C16: Urvashi | D16: Add to nurture list for next batch | E16: Within 1 wk | F16: Update Sheet: Status → Nurture. Follow up in 3 weeks for next batch. | G16: Manual

Sheet 💰 Budget Tracker
A1: AD SPEND & LEAD TRACKER — Summer 2026
A2: Fill in Leads Generated and Trials Booked each week. All other columns auto-calculate.
A4: Week | B4: Ad Set / Channel | C4: Daily Budget (₹) | D4: Days Running | E4: Spend (₹) | F4: Leads Generated | G4: Cost per Lead (₹) | H4: Trials Booked | I4: Enrolled | J4: Notes
A5: 1 | B5: Ad Set 1 — Students (Angle A) | C5: 100 | D5: 7 | E5: =C5*D5 | F5: 0 | G5: =IF(F5>0,E5/F5,"—") | H5: 0 | I5: 0 | J5: Launch week
A6: 1 | B6: Ad Set 2 — Homemakers (Angle B) | C6: 100 | D6: 7 | E6: =C6*D6 | F6: 0 | G6: =IF(F6>0,E6/F6,"—") | H6: 0 | I6: 0 | J6: Launch week
A7: 1 | B7: Boosted Post (top organic) | C7: 0 | D7: 0 | E7: =C7*D7 | F7: 0 | G7: =IF(F7>0,E7/F7,"—") | H7: 0 | I7: 0 | J7: Only if strong organic post
A8: 2 | B8: Ad Set 1 (continued) | C8: 100 | D8: 7 | E8: =C8*D8 | F8: 0 | G8: =IF(F8>0,E8/F8,"—") | H8: 0 | I8: 0
A9: 2 | B9: Ad Set 2 (continued) | C9: 100 | D9: 7 | E9: =C9*D9 | F9: 0 | G9: =IF(F9>0,E9/F9,"—") | H9: 0 | I9: 0
A10: 2 | B10: Boosted Post | C10: 200 | D10: 3 | E10: =C10*D10 | F10: 0 | G10: =IF(F10>0,E10/F10,"—") | H10: 0 | I10: 0 | J10: Boost best Reel from Wk 1
A11: 3 | B11: Ad Set winner (double) | C11: 200 | D11: 7 | E11: =C11*D11 | F11: 0 | G11: =IF(F11>0,E11/F11,"—") | H11: 0 | I11: 0 | J11: Kill loser ad set
A12: 4 | B12: Ad Set winner | C12: 200 | D12: 7 | E12: =C12*D12 | F12: 0 | G12: =IF(F12>0,E12/F12,"—") | H12: 0 | I12: 0
A13: 4 | B13: Retargeting — Angle E | C13: 65 | D13: 7 | E13: =C13*D13 | F13: 0 | G13: =IF(F13>0,E13/F13,"—") | H13: 0 | I13: 0 | J13: Page visitors
A14: 5 | B14: Ad Set winner (scale 2x) | C14: 300 | D14: 7 | E14: =C14*D14 | F14: 0 | G14: =IF(F14>0,E14/F14,"—") | H14: 0 | I14: 0
A15: 5 | B15: Retargeting | C15: 65 | D15: 7 | E15: =C15*D15 | F15: 0 | G15: =IF(F15>0,E15/F15,"—") | H15: 0 | I15: 0
A16: 6 | B16: Ad Set winner | C16: 300 | D16: 7 | E16: =C16*D16 | F16: 0 | G16: =IF(F16>0,E16/F16,"—") | H16: 0 | I16: 0
A17: 6 | B17: Urgency — Angle D | C17: 100 | D17: 7 | E17: =C17*D17 | F17: 0 | G17: =IF(F17>0,E17/F17,"—") | H17: 0 | I17: 0
A18: 7 | B18: Max budget — winner | C18: 400 | D18: 7 | E18: =C18*D18 | F18: 0 | G18: =IF(F18>0,E18/F18,"—") | H18: 0 | I18: 0
A19: 8 | B19: Lookalike from leads list | C19: 300 | D19: 7 | E19: =C19*D19 | F19: 0 | G19: =IF(F19>0,E19/F19,"—") | H19: 0 | I19: 0 | J19: Export leads → create lookalike
A20: TOTAL | E20: =SUM(E5:E19) | F20: =SUM(F5:F19) | G20: =IF(F20>0,E20/F20,"—") | H20: =SUM(H5:H19) | I20: =SUM(I5:I19)
